<Properties StartupConfiguration="{C3E13A12-E063-4169-AEAF-D6EBC06DEC8B}|Default">
  <MonoDevelop.Ide.Workbench ActiveDocument="361Capstone/Models/ICart.cs">
    <Files>
      <File FileName="361Capstone/Models/CartProduct.cs" Line="15" Column="28" />
      <File FileName="361Capstone/Models/ICartProduct.cs" Line="8" Column="20" />
      <File FileName="361Capstone/Models/Cart.cs" Line="1" Column="1" />
      <File FileName="361Capstone/Models/ICart.cs" Line="1" Column="1" />
      <File FileName="361Capstone/Models/IUser.cs" Line="13" Column="17" />
    </Files>
    <Pads>
      <Pad Id="ProjectPad">
        <State name="__root__">
          <Node name="361Capstone" expanded="True">
            <Node name="Capstone" expanded="True">
              <Node name="Controllers" expanded="True" />
              <Node name="Models" expanded="True">
                <Node name="ICart.cs" selected="True" />
              </Node>
              <Node name="Tests" expanded="True">
                <Node name="TestsAccessor" expanded="True" />
              </Node>
            </Node>
          </Node>
        </State>
      </Pad>
      <Pad Id="ClassPad">
        <State name="__root__">
          <Node name="361Capstone" selected="True" />
        </State>
      </Pad>
    </Pads>
  </MonoDevelop.Ide.Workbench>
  <MonoDevelop.Ide.ItemProperties.Capstone PreferredExecutionTarget="/Applications/Brave Browser.app" />
  <MonoDevelop.Ide.DebuggingService.PinnedWatches />
  <MonoDevelop.Ide.Workspace ActiveConfiguration="Debug" />
  <MonoDevelop.Ide.DebuggingService.Breakpoints>
    <BreakpointStore>
      <Breakpoint file="/Users/jettdurante/Desktop/361Capstone/361Capstone/361Capstone/Accessors/DatabaseConnection.cs" relfile="361Capstone/Accessors/DatabaseConnection.cs" line="7" column="1" />
    </BreakpointStore>
  </MonoDevelop.Ide.DebuggingService.Breakpoints>
  <MultiItemStartupConfigurations />
</Properties>